IM/AppDB.py
IM/AppDBIS.py
IM/CloudInfo.py
IM/ConfManager.py
IM/CtxtAgentBase.py
IM/FedcloudInfo.py
IM/InfrastructureInfo.py
IM/InfrastructureList.py
IM/InfrastructureManager.py
IM/LoggerMixin.py
IM/REST.py
IM/SSH.py
IM/SSHRetry.py
IM/ServiceRequests.py
IM/Stats.py
IM/UnixHTTPAdapter.py
IM/VMRC.py
IM/VirtualMachine.py
IM/__init__.py
IM/auth.py
IM/config.py
IM/db.py
IM/im_service.py
IM/recipe.py
IM/request.py
IM/retry.py
IM/swagger_api.yaml
IM/timedcall.py
IM/vault.py
IM/xmlobject.py
IM/xmlrpcssl.py
IM/ansible_utils/__init__.py
IM/ansible_utils/ansible_executor_v2.py
IM/ansible_utils/ansible_launcher.py
IM/connectors/Azure.py
IM/connectors/CloudConnector.py
IM/connectors/CloudStack.py
IM/connectors/DeployedNode.py
IM/connectors/Docker.py
IM/connectors/Dummy.py
IM/connectors/EC2.py
IM/connectors/EGI.py
IM/connectors/FogBow.py
IM/connectors/GCE.py
IM/connectors/Kubernetes.py
IM/connectors/Lambda.py
IM/connectors/LibCloud.py
IM/connectors/Linode.py
IM/connectors/OCCI.py
IM/connectors/OSCAR.py
IM/connectors/OpenNebula.py
IM/connectors/OpenStack.py
IM/connectors/Orange.py
IM/connectors/__init__.py
IM/connectors/exceptions.py
IM/connectors/vSphere.py
IM/oaipmh/__init__.py
IM/oaipmh/errors.py
IM/oaipmh/oai.py
IM/oaipmh/utils.py
IM/openid/JWT.py
IM/openid/OpenIDClient.py
IM/openid/__init__.py
IM/tosca/Tosca.py
IM/tosca/__init__.py
IM/tts/__init__.py
IM/tts/onetts.py
IM/tts/tts.py
contextualization/__init__.py
contextualization/ansible_install.sh
contextualization/basic.yml
contextualization/conf-ansible.yml
contextualization/ctxt_agent.py
contextualization/ctxt_agent_dist.py
contextualization/recipes_ansible.db
contextualization/AnsibleRecipes/utils/tasks/del_oscar_function.yml
contextualization/AnsibleRecipes/utils/tasks/disk_format_mount.yml
contextualization/AnsibleRecipes/utils/tasks/main.yml
contextualization/AnsibleRecipes/utils/tasks/oscar_function.yml
contextualization/AnsibleRecipes/utils/templates/epel-es.repo
im-1.19.1.dist-info/LICENSE
im-1.19.1.dist-info/METADATA
im-1.19.1.dist-info/NOTICE
im-1.19.1.dist-info/WHEEL
im-1.19.1.dist-info/entry_points.txt
im-1.19.1.dist-info/top_level.txt
im-1.19.1.dist-info/RECORD
