Metadata-Version: 2.1
Name: im
Version: 1.19.1
Summary: IM is a tool to manage virtual infrastructures on Cloud deployments
License: GPL version 3, http://www.gnu.org/licenses/gpl-3.0.txt
Project-URL: Homepage, https://www.grycap.upv.es/im
Project-URL: Documentation, https://imdocs.readthedocs.io
Project-URL: Repository, https://github.com/grycap/im
Classifier: Development Status :: 5 - Production/Stable
Classifier: Intended Audience :: Developers
Classifier: Intended Audience :: System Administrators
Classifier: Operating System :: OS Independent
Classifier: Framework :: CherryPy
Classifier: Framework :: Flask
Classifier: License :: OSI Approved :: GNU General Public License v3 (GPLv3)
Classifier: Programming Language :: Python
Classifier: Programming Language :: Python :: 3
Classifier: Programming Language :: Python :: 3.6
Classifier: Programming Language :: Python :: 3.7
Classifier: Programming Language :: Python :: 3.8
Classifier: Programming Language :: Python :: 3.9
Classifier: Programming Language :: Python :: 3.10
Classifier: Programming Language :: Python :: 3.11
Requires-Python: >=3.6
License-File: LICENSE
Requires-Dist: ansible (>=2.4)
Requires-Dist: paramiko (>=1.14)
Requires-Dist: PyYAML
Requires-Dist: suds-community
Requires-Dist: cheroot
Requires-Dist: boto3
Requires-Dist: apache-libcloud (>=3.2.0)
Requires-Dist: RADL (>=1.3.3)
Requires-Dist: flask
Requires-Dist: netaddr
Requires-Dist: requests (>=2.19)
Requires-Dist: scp
Requires-Dist: tosca-parser
Requires-Dist: defusedxml
Requires-Dist: urllib3 (>=1.23)
Requires-Dist: hvac
Requires-Dist: psutil
Requires-Dist: scar
Requires-Dist: requests-cache (>=1.0.0)
Requires-Dist: packaging
Requires-Dist: werkzeug
Requires-Dist: xmltodict
Requires-Dist: lxml
Provides-Extra: build
Requires-Dist: build (==1.0.3) ; extra == 'build'
Provides-Extra: publish
Requires-Dist: twine (==4.0.2) ; extra == 'publish'
Provides-Extra: test
Requires-Dist: mock ; extra == 'test'
Requires-Dist: coverage ; extra == 'test'
